{
  "tournament": {
    "name": "FIFA Dünya Kupası 2026",
    "slug": "wc2026",
    "start_date": "2026-06-11",
    "end_date": "2026-07-19",
    "timezone": "Europe/Istanbul",
    "is_active": true
  },
  "stages": [
    {"kind": "GROUP",  "order": 0, "points_exact": 6,  "points_diff": 4,  "points_result": 2, "penalty_loser_pct": "0.60"},
    {"kind": "R32",    "order": 1, "points_exact": 7,  "points_diff": 5,  "points_result": 3, "penalty_loser_pct": "0.60"},
    {"kind": "R16",    "order": 2, "points_exact": 9,  "points_diff": 6,  "points_result": 3, "penalty_loser_pct": "0.60"},
    {"kind": "QF",     "order": 3, "points_exact": 14, "points_diff": 9,  "points_result": 5, "penalty_loser_pct": "0.60"},
    {"kind": "SF",     "order": 4, "points_exact": 20, "points_diff": 14, "points_result": 7, "penalty_loser_pct": "0.60"},
    {"kind": "THIRD",  "order": 5, "points_exact": 20, "points_diff": 14, "points_result": 7, "penalty_loser_pct": "0.60"},
    {"kind": "FINAL",  "order": 6, "points_exact": 20, "points_diff": 14, "points_result": 7, "penalty_loser_pct": "0.60"}
  ],
  "prediction_rounds": [
    {"order": 0, "name": "Pre-turnuva",   "weight": "1.00", "editable_stages": ["GROUP", "R32", "R16", "QF", "SF", "THIRD", "FINAL"], "depends_on_stage": null},
    {"order": 1, "name": "Grup sonrası",  "weight": "0.85", "editable_stages": ["R32", "R16", "QF", "SF", "THIRD", "FINAL"],          "depends_on_stage": "GROUP"},
    {"order": 2, "name": "R32 sonrası",   "weight": "0.75", "editable_stages": ["R16", "QF", "SF", "THIRD", "FINAL"],                 "depends_on_stage": "R32"},
    {"order": 3, "name": "R16 sonrası",   "weight": "0.65", "editable_stages": ["QF", "SF", "THIRD", "FINAL"],                        "depends_on_stage": "R16"},
    {"order": 4, "name": "QF sonrası",    "weight": "0.55", "editable_stages": ["SF", "THIRD", "FINAL"],                              "depends_on_stage": "QF"},
    {"order": 5, "name": "SF sonrası",    "weight": "0.45", "editable_stages": ["THIRD", "FINAL"],                                    "depends_on_stage": "SF"}
  ]
}
